{
    "$ D %Mark with X": "$ D %Mark with X",
    "$ D %Mark with phone": "$ D %Mark with phone",
    "$ D scene envi normal": "$ D scene envi normal",
    "$ F %Mark dazed": "$ F %Mark dazed",
    "$ F %Mark default": "$ F %Mark default",
    "$ hide_phone": "$ hide_phone",
    "$ pass": "$ pass",
    "$ play_sound SoundFromLeft": "$ play_sound SoundFromLeft",
    "$ pop_focus F0": "$ pop_focus F0",
    "$ push_focus F0": "$ push_focus F0",
    "$ push_named \"/chat\"": "$ push_named \"/chat\"",
    "$ say KateCorpuz \"Huh? Who's there?\"": "$ say KateCorpuz \"Huh? Who's there?\"",
    "$ show_phone": "$ show_phone",
    "$ start \"lo.7.3.FreeRoam.1c\"": "$ start \"lo.7.3.FreeRoam.1c\"",
    "$ start_short mark_footstep_reaction": "$ start_short mark_footstep_reaction",
    "$ thought \"Is that...\"": "$ thought \"Is that...\"",
    "$ thought \"It's almost as I remember it.\"": "$ thought \"It's almost as I remember it.\"",
    "$ to CamWalk": "$ to CamWalk",
    "$ wait 0.5": "$ wait 0.5",
    "$ wait 1": "$ wait 1",
    "$ wait 1.5": "$ wait 1.5",
    "$ wait_for _scene_faded_in": "$ wait_for _scene_faded_in",
    "$ wait_for approach_kate": "$ wait_for approach_kate",
    "$ wait_for hear_footsteps": "$ wait_for hear_footsteps",
    "$ wait_for house_reached": "$ wait_for house_reached",
    "$ wait_for nicole_chat_finished": "$ wait_for nicole_chat_finished",
    "$ wait_for start_chat_nicole": "$ wait_for start_chat_nicole",
    "characters: { \"Mark\": \"MarkBorja\" }": "characters: { \"Mark\": \"MarkBorja\" }",
    "hide_back_btn: true": "hide_back_btn: true",
    "id: \"lo.7.3.FreeRoam.1c\"": "id: \"lo.7.3.FreeRoam.1c\"",
    "player: \"Mark\"": "player: \"Mark\"",
    "type: \"scene\"": "type: \"scene\""
}