{
    "$ ": "$ ",
    "$ F CutsceneCathy jaded": "$ F CutsceneCathy jaded",
    "$ F CutsceneCathy joyful": "$ F CutsceneCathy joyful",
    "$ F CutsceneCathy positive": "$ F CutsceneCathy positive",
    "$ F CutsceneCathy speechless": "$ F CutsceneCathy speechless",
    "$ F CutsceneCathy suspicious": "$ F CutsceneCathy suspicious",
    "$ F CutsceneCathy thinking": "$ F CutsceneCathy thinking",
    "$ F CutsceneMark checking": "$ F CutsceneMark checking",
    "$ F CutsceneMark smirkrock": "$ F CutsceneMark smirkrock",
    "$ pass": "$ pass",
    "$ to CamCutscene": "$ to CamCutscene",
    "$ wait 0.25": "$ wait 0.25",
    "$ wait 0.5": "$ wait 0.5",
    "$ wait 1": "$ wait 1",
    "$ wait 1.5": "$ wait 1.5",
    "CutsceneCathy: And it went to nothing?": "CutsceneCathy: And it went to nothing?",
    "CutsceneCathy: Four?": "CutsceneCathy: Four?",
    "CutsceneCathy: How could you keep such a juicy piece of information from me?": "CutsceneCathy: How could you keep such a juicy piece of information from me?",
    "CutsceneCathy: Lookin' fancy today, huh?": "CutsceneCathy: Lookin' fancy today, huh?",
    "CutsceneCathy: Pfft, you're so love-struck.": "CutsceneCathy: Pfft, you're so love-struck.",
    "CutsceneCathy: So that was how many dates again?": "CutsceneCathy: So that was how many dates again?",
    "CutsceneCathy: You know you still have to get me a dress for Ridel's premiere, right?": "CutsceneCathy: You know you still have to get me a dress for Ridel's premiere, right?",
    "CutsceneCathy: You've been talking to someone?": "CutsceneCathy: You've been talking to someone?",
    "CutsceneCathy: [wave]I'm wounded, Mark![.] Gobsmacked![/wave]": "CutsceneCathy: [wave]I'm wounded, Mark![.] Gobsmacked![/wave]",
    "CutsceneCathy: [wave]Now that's confidence![/wave]": "CutsceneCathy: [wave]Now that's confidence![/wave]",
    "CutsceneCathy: [wave]Oh-ho-ho![/wave]": "CutsceneCathy: [wave]Oh-ho-ho![/wave]",
    "CutsceneMark: And you'll love it.": "CutsceneMark: And you'll love it.",
    "CutsceneMark: Calm down.": "CutsceneMark: Calm down.",
    "CutsceneMark: Haha, yeah[.], that sucked[.], but...": "CutsceneMark: Haha, yeah[.], that sucked[.], but...",
    "CutsceneMark: I've got a date.": "CutsceneMark: I've got a date.",
    "CutsceneMark: I've got a good feeling about this one.": "CutsceneMark: I've got a good feeling about this one.",
    "CutsceneMark: It's only the first date.": "CutsceneMark: It's only the first date.",
    "CutsceneMark: Oh, Cath.[.] I already did.": "CutsceneMark: Oh, Cath.[.] I already did.",
    "NOP": "NOP",
    "characters: { \"Mark\": \"MarkBorja\"}": "characters: { \"Mark\": \"MarkBorja\"}",
    "player: \"Mark\"": "player: \"Mark\"",
    "type: \"dialogue\"": "type: \"dialogue\""
}
