{
    " default": " default",
    " smirk": " smirk",
    " true": " true",
    "$ F ": "$ F ",
    "$ flip_h ": "$ flip_h ",
    "$ pass": "$ pass",
    "$ wait 0.5": "$ wait 0.5",
    "$ wait 1": "$ wait 1",
    "Louise: Anyway, Mark, don't worry too much.": "Louise: Anyway, Mark, don't worry too much.",
    "Louise: It should be all right tonight, Mark.": "Louise: It should be all right tonight, Mark.",
    "Louise: Let's just...[.] it'll be fine.": "Louise: Let's just...[.] it'll be fine.",
    "Louise: We're all in one place.": "Louise: We're all in one place.",
    "Mark: Got someone in mind?": "Mark: Got someone in mind?",
    "Mark: It's a big night after all.": "Mark: It's a big night after all.",
    "Mark: Just a bit worried about the rain...": "Mark: Just a bit worried about the rain...",
    "Mark: Oh...": "Mark: Oh...",
    "Mark: That's thanks to you.": "Mark: That's thanks to you.",
    "MarkBorja": "MarkBorja",
    "Sofia: A little rain could even be romantic!": "Sofia: A little rain could even be romantic!",
    "Sofia: A-and I must say...": "Sofia: A-and I must say...",
    "Sofia: And who knows?!": "Sofia: And who knows?!",
    "Sofia: Geez, will a raindrop kill you guys?": "Sofia: Geez, will a raindrop kill you guys?",
    "Sofia: Guys, hey, calm down!": "Sofia: Guys, hey, calm down!",
    "Sofia: I-I meant for you!": "Sofia: I-I meant for you!",
    "Sofia: It's prom night!": "Sofia: It's prom night!",
    "Sofia: Let's just have fun!": "Sofia: Let's just have fun!",
    "Sofia: Something wrong with the sky, Marky?!": "Sofia: Something wrong with the sky, Marky?!",
    "Sofia: There's a big ol' roof!": "Sofia: There's a big ol' roof!",
    "Sofia: We've got each other's backs, right?!": "Sofia: We've got each other's backs, right?!",
    "Sofia: You look great in your ensemble.": "Sofia: You look great in your ensemble.",
    "Sofia: You'll definitely catch her attention!": "Sofia: You'll definitely catch her attention!",
    "characters: { \"Mark\": \"MarkBorja\", \"Louise\": \"LouiseOrdunia\", \"Sofia\": \"SofiaRubio\" }": "characters: { \"Mark\": \"MarkBorja\", \"Louise\": \"LouiseOrdunia\", \"Sofia\": \"SofiaRubio\" }",
    "player: \"Mark\"": "player: \"Mark\"",
    "type: \"dialogue\"": "type: \"dialogue\""
}
