{
    " Sure, why not?": " Sure, why not?",
    "!\"": "!\"",
    "\"": "\"",
    "$ ": "$ ",
    "$ D %Mark with gamepad": "$ D %Mark with gamepad",
    "$ D %Mark with remote": "$ D %Mark with remote",
    "$ F %Mark": "$ F %Mark",
    "$ F %Mark empty": "$ F %Mark empty",
    "$ F %Mark focused": "$ F %Mark focused",
    "$ F %Mark gameface": "$ F %Mark gameface",
    "$ F %Mark scared": "$ F %Mark scared",
    "$ F %Mark triumphant": "$ F %Mark triumphant",
    "$ KLC_say Eiri \"It's nice meeting you, ": "$ KLC_say Eiri \"It's nice meeting you, ",
    "$ KLC_say Eiri \"Welcome to the club.\"": "$ KLC_say Eiri \"Welcome to the club.\"",
    "$ KLC_say Ichika \"Ah, you must be ": "$ KLC_say Ichika \"Ah, you must be ",
    "$ KLC_say Ichika \"Welcome to [wave]Kokoro Literature Club![/wave]\"": "$ KLC_say Ichika \"Welcome to [wave]Kokoro Literature Club![/wave]\"",
    "$ KLC_say Ichika \"What a nice surprise!\"": "$ KLC_say Ichika \"What a nice surprise!\"",
    "$ KLC_say MC \"...[wave]incredibly cute girls![/wave]\"": "$ KLC_say MC \"...[wave]incredibly cute girls![/wave]\"",
    "$ KLC_say MC \"There are no words.\"": "$ KLC_say MC \"There are no words.\"",
    "$ KLC_say MC \"This club is full of...\"": "$ KLC_say MC \"This club is full of...\"",
    "$ KLC_say Natsuki \"Way to kill the atmosphere!\"": "$ KLC_say Natsuki \"Way to kill the atmosphere!\"",
    "$ KLC_say Natsuki \"[shake rate=32 level=8]Seriously?[/shake] You brought a boy?!\"": "$ KLC_say Natsuki \"[shake rate=32 level=8]Seriously?[/shake] You brought a boy?!\"",
    "$ emit end_minigame_platformer": "$ emit end_minigame_platformer",
    "$ emit start_minigame_platformer": "$ emit start_minigame_platformer",
    "$ fade_in": "$ fade_in",
    "$ fade_out": "$ fade_out",
    "$ fade_out_sound --keep-vol DDLCOrig": "$ fade_out_sound --keep-vol DDLCOrig",
    "$ pass": "$ pass",
    "$ play --reverse turn_on_tv": "$ play --reverse turn_on_tv",
    "$ play ConsoleBoot_boot": "$ play ConsoleBoot_boot",
    "$ play KLC_enter_ichika": "$ play KLC_enter_ichika",
    "$ play KLC_enter_natsuki": "$ play KLC_enter_natsuki",
    "$ play TestCard_show_indicator": "$ play TestCard_show_indicator",
    "$ play turn_on_tv": "$ play turn_on_tv",
    "$ play_anim %Mark emptying": "$ play_anim %Mark emptying",
    "$ play_anim --force MarkHint notice": "$ play_anim --force MarkHint notice",
    "$ play_sound DDLCOrig": "$ play_sound DDLCOrig",
    "$ play_sound DDLCScary": "$ play_sound DDLCScary",
    "$ play_sound PS3Boot": "$ play_sound PS3Boot",
    "$ play_sound PS3Nav": "$ play_sound PS3Nav",
    "$ play_sound RPGBattle": "$ play_sound RPGBattle",
    "$ play_sound RPGButtonPress": "$ play_sound RPGButtonPress",
    "$ play_sound RPGCharSelect": "$ play_sound RPGCharSelect",
    "$ play_sound RPGMainMenu": "$ play_sound RPGMainMenu",
    "$ play_sound TVActionScene": "$ play_sound TVActionScene",
    "$ play_sound TVLateNightShow": "$ play_sound TVLateNightShow",
    "$ play_sound TVMonotone": "$ play_sound TVMonotone",
    "$ play_sound TVSigningOff": "$ play_sound TVSigningOff",
    "$ play_sound TVTelenovela": "$ play_sound TVTelenovela",
    "$ start_short \"action_scene\"": "$ start_short \"action_scene\"",
    "$ start_short \"talkshow\"": "$ start_short \"talkshow\"",
    "$ start_short \"telenovela\"": "$ start_short \"telenovela\"",
    "$ start_short \"tv_station_end\"": "$ start_short \"tv_station_end\"",
    "$ stop_sound DDLCScary": "$ stop_sound DDLCScary",
    "$ stop_sound PS3Nav": "$ stop_sound PS3Nav",
    "$ stop_sound RPGBattle": "$ stop_sound RPGBattle",
    "$ stop_sound RPGCharSelect": "$ stop_sound RPGCharSelect",
    "$ stop_sound RPGMainMenu": "$ stop_sound RPGMainMenu",
    "$ stop_sound TVActionScene": "$ stop_sound TVActionScene",
    "$ stop_sound TVLateNightShow": "$ stop_sound TVLateNightShow",
    "$ stop_sound TVMonotone": "$ stop_sound TVMonotone",
    "$ stop_sound TVSigningOff": "$ stop_sound TVSigningOff",
    "$ stop_sound TVTelenovela": "$ stop_sound TVTelenovela",
    "$ switch_sound MusicMain Main": "$ switch_sound MusicMain Main",
    "$ switch_sound MusicMain X": "$ switch_sound MusicMain X",
    "$ thought \"": "$ thought \"",
    "$ to ": "$ to ",
    "$ to \"": "$ to \"",
    "$ to SitSofa": "$ to SitSofa",
    "$ to_tv_screen ConsoleBoot": "$ to_tv_screen ConsoleBoot",
    "$ to_tv_screen KLC": "$ to_tv_screen KLC",
    "$ to_tv_screen MinigamePlatformer": "$ to_tv_screen MinigamePlatformer",
    "$ to_tv_screen MmoCharSelect": "$ to_tv_screen MmoCharSelect",
    "$ to_tv_screen MmoLevelUp": "$ to_tv_screen MmoLevelUp",
    "$ to_tv_screen TestCard": "$ to_tv_screen TestCard",
    "$ wait 0.25": "$ wait 0.25",
    "$ wait 0.5": "$ wait 0.5",
    "$ wait 1": "$ wait 1",
    "$ wait 1.5": "$ wait 1.5",
    "$ wait 2": "$ wait 2",
    "$ wait 3": "$ wait 3",
    "$ wait 3.5": "$ wait 3.5",
    "$ wait 4": "$ wait 4",
    "$ wait_for minigame_platformer_finished": "$ wait_for minigame_platformer_finished",
    ".\"": ".\"",
    "Better try something else.": "Better try something else.",
    "But never bothered to touch.": "But never bothered to touch.",
    "C3D_13": "C3D_13",
    "Forget it.": "Forget it.",
    "I don't think I'll resort to TV ever again.": "I don't think I'll resort to TV ever again.",
    "I just gotta win a couple matches and I'll level up again.": "I just gotta win a couple matches and I'll level up again.",
    "ILoveSuckingLemons": "ILoveSuckingLemons",
    "If I had to choose now, I'd probably date Eiri.": "If I had to choose now, I'd probably date Eiri.",
    "Into the trash folder you go.": "Into the trash folder you go.",
    "It's almost midnight indeed.": "It's almost midnight indeed.",
    "Just a bunch of games on sale I impulsively bought...": "Just a bunch of games on sale I impulsively bought...",
    "Let's see. What do we have here?": "Let's see. What do we have here?",
    "Let's watch local TV[.], just like everyone else with internet totally does.": "Let's watch local TV[.], just like everyone else with internet totally does.",
    "Ooh, this one looks cute.": "Ooh, this one looks cute.",
    "SitSofa": "SitSofa",
    "TVScreen": "TVScreen",
    "That'll get me going for sure!": "That'll get me going for sure!",
    "This seems fun. I can take this.": "This seems fun. I can take this.",
    "[shake rate=16 level=6]Oh my God. That's it! I'm outta here![/shake]": "[shake rate=16 level=6]Oh my God. That's it! I'm outta here![/shake]",
    "[shake rate=32 level=8]Oh shit![/shake]": "[shake rate=32 level=8]Oh shit![/shake]",
    "[wave]Oh yeah.[/wave]": "[wave]Oh yeah.[/wave]",
    "[wave]That's what I'm talkin' about, baby![/wave]": "[wave]That's what I'm talkin' about, baby![/wave]",
    "[wave]Yeah!![/wave]": "[wave]Yeah!![/wave]",
    "base_color: \"000000\"": "base_color: \"000000\"",
    "base_color: \"673497\"": "base_color: \"673497\"",
    "base_color: \"73b654\"": "base_color: \"73b654\"",
    "base_color: \"9e68ff\"": "base_color: \"9e68ff\"",
    "base_color: \"b3baff\"": "base_color: \"b3baff\"",
    "base_color: \"bc97ff\"": "base_color: \"bc97ff\"",
    "base_color: \"dfffdc\"": "base_color: \"dfffdc\"",
    "base_color: \"fbde7c\"": "base_color: \"fbde7c\"",
    "base_color: \"feffcb\"": "base_color: \"feffcb\"",
    "base_color: \"ff0101\"": "base_color: \"ff0101\"",
    "base_color: \"ffc6f8\"": "base_color: \"ffc6f8\"",
    "base_color: \"fffce7\"": "base_color: \"fffce7\"",
    "base_color: \"ffffff\"": "base_color: \"ffffff\"",
    "characters: { \"Mark\": \"MarkBorja\" }": "characters: { \"Mark\": \"MarkBorja\" }",
    "h_random: 0.0": "h_random: 0.0",
    "h_random: 0.05": "h_random: 0.05",
    "h_random: 0.08": "h_random: 0.08",
    "h_random: 0.1": "h_random: 0.1",
    "h_random: 0.15": "h_random: 0.15",
    "player: \"Mark\"": "player: \"Mark\"",
    "set_tv_far_light_props": "set_tv_far_light_props",
    "speed: 1.0": "speed: 1.0",
    "speed: 128.0": "speed: 128.0",
    "speed: 50.0": "speed: 50.0",
    "speed: 60.0": "speed: 60.0",
    "speed: 750.0": "speed: 750.0",
    "type: \"scene\"": "type: \"scene\""
}