{
    "\"": "\"",
    "$ D NicoleLacsamana look_at X": "$ D NicoleLacsamana look_at X",
    "$ D NicoleLacsamana look_at r": "$ D NicoleLacsamana look_at r",
    "$ D NicoleLacsamana with X": "$ D NicoleLacsamana with X",
    "$ D NicoleLacsamana with sit": "$ D NicoleLacsamana with sit",
    "$ D NicoleLacsamana with sitphone": "$ D NicoleLacsamana with sitphone",
    "$ F NicoleLacsamana concerned": "$ F NicoleLacsamana concerned",
    "$ F NicoleLacsamana neutral": "$ F NicoleLacsamana neutral",
    "$ clear_phone": "$ clear_phone",
    "$ next_scene": "$ next_scene",
    "$ pass": "$ pass",
    "$ play_sound MetalCreak": "$ play_sound MetalCreak",
    "$ pop_focus F0": "$ pop_focus F0",
    "$ push_focus F0": "$ push_focus F0",
    "$ push_named \"/chat\"": "$ push_named \"/chat\"",
    "$ show_phone": "$ show_phone",
    "$ start \"lo.3.2a.1c\"": "$ start \"lo.3.2a.1c\"",
    "$ thought \"": "$ thought \"",
    "$ to CamMain": "$ to CamMain",
    "$ wait 1": "$ wait 1",
    "$ wait 2": "$ wait 2",
    "$ wait 3": "$ wait 3",
    "$ wait_for _scene_faded_in": "$ wait_for _scene_faded_in",
    "$ wait_for go_downstairs": "$ wait_for go_downstairs",
    "$ wait_for nicole_chat_finished": "$ wait_for nicole_chat_finished",
    "God[.], Mark is right.[.] It's not supposed to be this bad.": "God[.], Mark is right.[.] It's not supposed to be this bad.",
    "So, this is me.": "So, this is me.",
    "Was me.": "Was me.",
    "characters: { \"Nicole\": \"NicoleLacsamana\" }": "characters: { \"Nicole\": \"NicoleLacsamana\" }",
    "hide_back_btn: true": "hide_back_btn: true",
    "id: \"lo.3.2a.1c\"": "id: \"lo.3.2a.1c\"",
    "player: \"Nicole\"": "player: \"Nicole\"",
    "type: \"scene\"": "type: \"scene\""
}
