{
    " ": " ",
    " cointoss_score": " cointoss_score",
    " false": " false",
    " true": " true",
    "$ ": "$ ",
    "$ chibi.set_active ": "$ chibi.set_active ",
    "$ chibi.set_anim ": "$ chibi.set_anim ",
    "$ chibi.shake ": "$ chibi.shake ",
    "$ cointoss.add_agent ": "$ cointoss.add_agent ",
    "$ cointoss.aim_position 2 0.2": "$ cointoss.aim_position 2 0.2",
    "$ cointoss.aim_position 3 0.2": "$ cointoss.aim_position 3 0.2",
    "$ cointoss.end_agent_turn": "$ cointoss.end_agent_turn",
    "$ cointoss.start_agent_turn ": "$ cointoss.start_agent_turn ",
    "$ cointoss.start_aim_strength": "$ cointoss.start_aim_strength",
    "$ cointoss.toss ": "$ cointoss.toss ",
    "$ fade_in": "$ fade_in",
    "$ pass": "$ pass",
    "$ pop_focus ": "$ pop_focus ",
    "$ push_focus ": "$ push_focus ",
    "$ to GameCoinToss": "$ to GameCoinToss",
    "$ wait ": "$ wait ",
    "$ wait 0.5": "$ wait 0.5",
    "$ wait 0.75": "$ wait 0.75",
    "$ wait 1": "$ wait 1",
    "$ wait 1.5": "$ wait 1.5",
    "1": "1",
    "2": "2",
    "Cathy: Get it started, Ridel!": "Cathy: Get it started, Ridel!",
    "Cathy: It's all in the flick of the wrist, my friend.": "Cathy: It's all in the flick of the wrist, my friend.",
    "Cathy: Remember boys, gotta get it completely in the box.": "Cathy: Remember boys, gotta get it completely in the box.",
    "Cathy: This game is rigged!": "Cathy: This game is rigged!",
    "Cathy: You mean [wave]two girlfriends[/wave]?": "Cathy: You mean [wave]two girlfriends[/wave]?",
    "CathyPortillo": "CathyPortillo",
    "D_get ": "D_get ",
    "Mark: I am a master.": "Mark: I am a master.",
    "Mark: My turn.": "Mark: My turn.",
    "Mark: Obviously, I suck at this.": "Mark: Obviously, I suck at this.",
    "Mark: Oh shut up.": "Mark: Oh shut up.",
    "Mark: Watch and learn.": "Mark: Watch and learn.",
    "MarkBorja": "MarkBorja",
    "MinigameCoinToss": "MinigameCoinToss",
    "NOP": "NOP",
    "Ridel: It's like he leveled up because he has a girlfriend now.": "Ridel: It's like he leveled up because he has a girlfriend now.",
    "Ridel: Man, just enjoy the game.": "Ridel: Man, just enjoy the game.",
    "Ridel: Man...[.] you're literally using your own coins.": "Ridel: Man...[.] you're literally using your own coins.",
    "Ridel: More like the flick of fortune.": "Ridel: More like the flick of fortune.",
    "Ridel: That's two levels up.": "Ridel: That's two levels up.",
    "Ridel: Uh-huh.": "Ridel: Uh-huh.",
    "Ridel: Why is this so hard?": "Ridel: Why is this so hard?",
    "Ridel: You're thinking of your girlfriend too much.": "Ridel: You're thinking of your girlfriend too much.",
    "Ridel: You're thinking of your girlfriend's research too much.": "Ridel: You're thinking of your girlfriend's research too much.",
    "RidelGonzales": "RidelGonzales",
    "angry": "angry",
    "ch8sc2a/for_research": "ch8sc2a/for_research",
    "characters: { \"Mark\": \"MarkBorja\", \"Cathy\": \"CathyPortillo\", \"Ridel\": \"RidelGonzales\" }": "characters: { \"Mark\": \"MarkBorja\", \"Cathy\": \"CathyPortillo\", \"Ridel\": \"RidelGonzales\" }",
    "cointoss.player_has_highest_score": "cointoss.player_has_highest_score",
    "confused": "confused",
    "focus": "focus",
    "idle": "idle",
    "miss": "miss",
    "player: \"Mark\"": "player: \"Mark\"",
    "positive": "positive",
    "type: \"dialogue\"": "type: \"dialogue\"",
    "wait_for cointoss.tossed": "wait_for cointoss.tossed"
}
