{
    " concerned": " concerned",
    " determined": " determined",
    " false": " false",
    " look_at X": " look_at X",
    " look_at d": " look_at d",
    " serious": " serious",
    " with X": " with X",
    " with laser": " with laser",
    " with phone": " with phone",
    " with run": " with run",
    "\"": "\"",
    "$ ": "$ ",
    "$ D ": "$ D ",
    "$ D scene glitch 0": "$ D scene glitch 0",
    "$ D scene glitch 0.3": "$ D scene glitch 0.3",
    "$ F ": "$ F ",
    "$ flip_h ": "$ flip_h ",
    "$ pass": "$ pass",
    "$ play --no-wait settle_down": "$ play --no-wait settle_down",
    "$ play --reverse --no-wait Mark_glitch_in": "$ play --reverse --no-wait Mark_glitch_in",
    "$ play --reverse flash_in": "$ play --reverse flash_in",
    "$ play CamPhoneDrop_drop": "$ play CamPhoneDrop_drop",
    "$ play Mark_glitch_hint": "$ play Mark_glitch_hint",
    "$ play_sound FootstepsSfx": "$ play_sound FootstepsSfx",
    "$ pop_focus F0": "$ pop_focus F0",
    "$ push_focus F0": "$ push_focus F0",
    "$ scroller.enqueue_special 0": "$ scroller.enqueue_special 0",
    "$ scroller.set_speed 0 0": "$ scroller.set_speed 0 0",
    "$ scroller.set_speed 0 0.2": "$ scroller.set_speed 0 0.2",
    "$ scroller.set_speed 2.7 0": "$ scroller.set_speed 2.7 0",
    "$ stop_sound FootstepsSfx": "$ stop_sound FootstepsSfx",
    "$ to ": "$ to ",
    "$ to \"": "$ to \"",
    "$ to CamPhoneDrop": "$ to CamPhoneDrop",
    "$ wait 0": "$ wait 0",
    "$ wait 0.1": "$ wait 0.1",
    "$ wait 0.2": "$ wait 0.2",
    "$ wait 0.25": "$ wait 0.25",
    "$ wait 0.3": "$ wait 0.3",
    "$ wait 0.4": "$ wait 0.4",
    "$ wait 0.5": "$ wait 0.5",
    "$ wait 0.75": "$ wait 0.75",
    "$ wait 1": "$ wait 1",
    "$ wait 1.5": "$ wait 1.5",
    "$ wait 2": "$ wait 2",
    "$ wait 2.5": "$ wait 2.5",
    "$ wait_for section_end_reached": "$ wait_for section_end_reached",
    ":: [shake rate=24 level=6]": ":: [shake rate=24 level=6]",
    "Alright. Either way will take me to the highway.": "Alright. Either way will take me to the highway.",
    "CamMain": "CamMain",
    "CamSS_C3D_Louise": "CamSS_C3D_Louise",
    "CamSS_Laser": "CamSS_Laser",
    "CamSS_Main": "CamSS_Main",
    "Cath!!": "Cath!!",
    "Come on, Mark.": "Come on, Mark.",
    "D_get scene MomPast_triggered": "D_get scene MomPast_triggered",
    "I have to find her!": "I have to find her!",
    "Louise: It's getting stronger.": "Louise: It's getting stronger.",
    "Louise: No, it doesn't.": "Louise: No, it doesn't.",
    "LouiseOrdunia": "LouiseOrdunia",
    "MarkBorja": "MarkBorja",
    "NOP": "NOP",
    "Nicole: Answer.": "Nicole: Answer.",
    "Nicole: Come on, Mark.": "Nicole: Come on, Mark.",
    "Nicole: I'll call him.": "Nicole: I'll call him.",
    "Nicole: That doesn't look good.": "Nicole: That doesn't look good.",
    "NicoleLacsamana": "NicoleLacsamana",
    "No...[.] th-that's not-": "No...[.] th-that's not-",
    "[/shake]": "[/shake]",
    "characters: { \"Mark\": \"MarkBorja\", \"Nicole\": \"NicoleLacsamana\", \"Louise\": \"LouiseOrdunia\" }": "characters: { \"Mark\": \"MarkBorja\", \"Nicole\": \"NicoleLacsamana\", \"Louise\": \"LouiseOrdunia\" }",
    "duration: 0.5": "duration: 0.5",
    "player: \"Mark\"": "player: \"Mark\"",
    "type: \"dialogue\"": "type: \"dialogue\""
}
