{
    " ": " ",
    " look_at ": " look_at ",
    " with ": " with ",
    "$ D ": "$ D ",
    "$ D MarkBorja with X": "$ D MarkBorja with X",
    "$ D MarkBorja with walk": "$ D MarkBorja with walk",
    "$ D NicoleLacsamana with X": "$ D NicoleLacsamana with X",
    "$ D NicoleLacsamana with walk": "$ D NicoleLacsamana with walk",
    "$ F ": "$ F ",
    "$ fade_in": "$ fade_in",
    "$ fade_out": "$ fade_out",
    "$ minigame_carving.finish": "$ minigame_carving.finish",
    "$ minigame_carving.set_enabled false": "$ minigame_carving.set_enabled false",
    "$ minigame_carving.set_enabled true": "$ minigame_carving.set_enabled true",
    "$ pass": "$ pass",
    "$ play_sound DogsBarking": "$ play_sound DogsBarking",
    "$ play_sound FootstepsMark": "$ play_sound FootstepsMark",
    "$ play_sound FootstepsNicole": "$ play_sound FootstepsNicole",
    "$ sidewalk.set_move_speed 0": "$ sidewalk.set_move_speed 0",
    "$ sidewalk.set_move_speed 0.8": "$ sidewalk.set_move_speed 0.8",
    "$ sidewalk.spawn Footbridge": "$ sidewalk.spawn Footbridge",
    "$ sidewalk.spawn Tree": "$ sidewalk.spawn Tree",
    "$ stop_sound FootstepsMark": "$ stop_sound FootstepsMark",
    "$ stop_sound FootstepsNicole": "$ stop_sound FootstepsNicole",
    "$ to CamMain": "$ to CamMain",
    "$ to MinigameCarving": "$ to MinigameCarving",
    "$ wait 0.5": "$ wait 0.5",
    "$ wait 0.75": "$ wait 0.75",
    "$ wait 1": "$ wait 1",
    "$ wait 10": "$ wait 10",
    "$ wait 12": "$ wait 12",
    "$ wait 2": "$ wait 2",
    "$ wait 8": "$ wait 8",
    "$ wait_for _scene_faded_in": "$ wait_for _scene_faded_in",
    "$ wait_for footbridge_reached": "$ wait_for footbridge_reached",
    "$ wait_for tree_reached": "$ wait_for tree_reached",
    "Mark (1): You'll see.": "Mark (1): You'll see.",
    "Mark (1.5): Shh, you can't rush art.": "Mark (1.5): Shh, you can't rush art.",
    "Mark (2): Now what shall I carve?": "Mark (2): Now what shall I carve?",
    "Mark: \"Innocent\" being the operative word.": "Mark: \"Innocent\" being the operative word.",
    "Mark: Aren't you glad?": "Mark: Aren't you glad?",
    "Mark: Do you think these memories are real?": "Mark: Do you think these memories are real?",
    "Mark: Galloping?": "Mark: Galloping?",
    "Mark: Hey, we should carve something too.": "Mark: Hey, we should carve something too.",
    "Mark: I dunno, to leave something": "Mark: I dunno, to leave something",
    "Mark: I guess we have to do this": "Mark: I guess we have to do this",
    "Mark: I maintain that you shouldn't have been in the middle of the hallway": "Mark: I maintain that you shouldn't have been in the middle of the hallway",
    "Mark: It feels like lifetimes ago...": "Mark: It feels like lifetimes ago...",
    "Mark: Look, a knife!": "Mark: Look, a knife!",
    "Mark: One last mark on this world?": "Mark: One last mark on this world?",
    "Mark: Perfect!": "Mark: Perfect!",
    "Mark: So...": "Mark: So...",
    "Mark: That they're ours?": "Mark: That they're ours?",
    "Mark: The tree or the knife?": "Mark: The tree or the knife?",
    "Mark: This is crazy, huh?": "Mark: This is crazy, huh?",
    "Mark: Well...": "Mark: Well...",
    "Mark: Y-yeah...": "Mark: Y-yeah...",
    "Mark: You just can't appreciate artistic genius!": "Mark: You just can't appreciate artistic genius!",
    "Mark: You wanna give it a go?": "Mark: You wanna give it a go?",
    "Mark: [wave]Hey![/wave]": "Mark: [wave]Hey![/wave]",
    "Mark: [wave]It was abstract![/wave]": "Mark: [wave]It was abstract![/wave]",
    "Mark: [wave]My masterpiece![/wave]": "Mark: [wave]My masterpiece![/wave]",
    "Mark: [wave]Voila![/wave]": "Mark: [wave]Voila![/wave]",
    "MarkBorja": "MarkBorja",
    "Nicole (1): Okay...": "Nicole (1): Okay...",
    "Nicole (1): What is that?": "Nicole (1): What is that?",
    "Nicole (1.5): Is this abstract, too?": "Nicole (1.5): Is this abstract, too?",
    "Nicole (2): I think I'm starting to see it a little.": "Nicole (2): I think I'm starting to see it a little.",
    "Nicole (2): Um, please be careful with that.": "Nicole (2): Um, please be careful with that.",
    "Nicole: And I maintain that you shouldn't have been galloping at full speed!": "Nicole: And I maintain that you shouldn't have been galloping at full speed!",
    "Nicole: And other times it wasn't!": "Nicole: And other times it wasn't!",
    "Nicole: How can we?": "Nicole: How can we?",
    "Nicole: How oddly convenient...": "Nicole: How oddly convenient...",
    "Nicole: I don't even want to know what that is.": "Nicole: I don't even want to know what that is.",
    "Nicole: I...[.] just don't know": "Nicole: I...[.] just don't know",
    "Nicole: It kind of was.": "Nicole: It kind of was.",
    "Nicole: It really is": "Nicole: It really is",
    "Nicole: It took way too long to get every last paint splatter off my uniform.": "Nicole: It took way too long to get every last paint splatter off my uniform.",
    "Nicole: It...": "Nicole: It...",
    "Nicole: Speaking of destruction...": "Nicole: Speaking of destruction...",
    "Nicole: Steamrolling ahead...": "Nicole: Steamrolling ahead...",
    "Nicole: The only thing we know right now is that...": "Nicole: The only thing we know right now is that...",
    "Nicole: Things keep getting worse when we meet": "Nicole: Things keep getting worse when we meet",
    "Nicole: Uh-huh, sure.": "Nicole: Uh-huh, sure.",
    "Nicole: Uh[.], I remember your art skills with that poster we always worked on?": "Nicole: Uh[.], I remember your art skills with that poster we always worked on?",
    "Nicole: Very nice, Pollock.": "Nicole: Very nice, Pollock.",
    "Nicole: Why would I destroy your masterpiece?": "Nicole: Why would I destroy your masterpiece?",
    "Nicole: Why?": "Nicole: Why?",
    "Nicole: With no concern for innocent bystanders.": "Nicole: With no concern for innocent bystanders.",
    "Nicole: Y-yeah, haha": "Nicole: Y-yeah, haha",
    "Nicole: Yeah...[.] I-I guess we do": "Nicole: Yeah...[.] I-I guess we do",
    "Nicole: You absolutely demolished that.": "Nicole: You absolutely demolished that.",
    "Nicole: You better let me do the work.": "Nicole: You better let me do the work.",
    "Nicole: You know...": "Nicole: You know...",
    "NicoleLacsamana": "NicoleLacsamana",
    "X": "X",
    "characters: { \"Mark\": \"MarkBorja\", \"Nicole\" : \"NicoleLacsamana\" }": "characters: { \"Mark\": \"MarkBorja\", \"Nicole\" : \"NicoleLacsamana\" }",
    "confusedpositive": "confusedpositive",
    "d": "d",
    "default": "default",
    "giggle": "giggle",
    "neutral": "neutral",
    "persuasive": "persuasive",
    "player: \"Mark\"": "player: \"Mark\"",
    "r": "r",
    "serious": "serious",
    "smirk": "smirk",
    "type: \"dialogue\"": "type: \"dialogue\""
}